<?xml version="1.0" encoding="UTF-8"?>
<?xml-stylesheet type="text/xsl" href="translator.xsl"?>

<DOCUMENT>
  <ParallelChunk annotation_id="0" docOffset="0">
    <en>Announcements by the President</en>
    <fr>Communications de la Présidence</fr>
  </ParallelChunk>
<Speaker annotation_id="31" id="006" name="President">
    <ParallelChunk annotation_id="31" docOffset="1">
      <en>In opening the last session of the European Parliament in 2009, I would firstly like to offer you all - all fellow Members - my sincere wishes for the approaching Christmas season, for the Chanukah festival, which has already begun, and for the coming new year.</en>
      <fr>
        <DiscourseConnective annotation_id="32">À</DiscourseConnective> l'occasion de l'ouverture de la dernière session du Parlement européen <DiscourseConnective annotation_id="105">pour</DiscourseConnective> 2009, je voudrais <DiscourseConnective annotation_id="128">avant</DiscourseConnective> toute chose présenter à tous mes collègues mes vœux sincères <DiscourseConnective annotation_id="195">à</DiscourseConnective> l'approche de la période de Noël, <DiscourseConnective annotation_id="231">pour</DiscourseConnective> la fête juive de Hanoucca, qui a <DiscourseConnective annotation_id="269">déjà</DiscourseConnective> commencé, <DiscourseConnective annotation_id="284">ainsi</DiscourseConnective> que <DiscourseConnective annotation_id="294">pour</DiscourseConnective> la prochaine nouvelle année.</fr>
    </ParallelChunk>
<ParallelChunk annotation_id="293" docOffset="2">
      <en>On behalf of all Members of the European Parliament, I would like to express similar sincere wishes to the administration, to all those who work directly with Parliament and assist us in our work.</en>
      <fr>Au nom de l'ensemble des députés du Parlement européen, je voudrais exprimer des vœux tout aussi sincères <DiscourseConnective annotation_id="434">à</DiscourseConnective> l'administration, <DiscourseConnective annotation_id="454">à</DiscourseConnective> tous ceux et celles qui travaillent directement avec le Parlement <DiscourseConnective annotation_id="522">et</DiscourseConnective> qui nous aident dans notre travail.</fr>
    </ParallelChunk>
<ParallelChunk annotation_id="490" docOffset="3">
      <en>I would <Alignment alignment="573" annotation_id="498">
          <DiscourseConnective annotation_id="498" sense="Expansion.Conjunction">also</DiscourseConnective>
        </Alignment> like to mention the attack on the Prime Minister of Italy, Silvio Berlusconi.</en>
      <fr>Je voudrais <Alignment alignment="223" annotation_id="573">
          <DiscourseConnective annotation_id="573" sense="Expansion.Conjunction">également</DiscourseConnective>
        </Alignment> vous parler de l'agression dont a été victime le Premier ministre italien, M. Silvio Berlusconi.</fr>
    </ParallelChunk>
<ParallelChunk annotation_id="581" docOffset="4">
      <en>The attack deserves our unequivocal condemnation.</en>
      <fr>Nous devons condamner sans la moindre équivoque cette agression.</fr>
    </ParallelChunk>
<ParallelChunk annotation_id="631" docOffset="5">
      <en>Political discussion must not be conducted in such a fashion.</en>
      <fr>On ne peut mener des discussions politiques d'une telle manière.</fr>
    </ParallelChunk>
<ParallelChunk annotation_id="693" docOffset="6">
      <en>Yesterday's incident should never have taken place.</en>
      <fr>L'incident d'hier n'aurait jamais dû se produire.</fr>
    </ParallelChunk>
<ParallelChunk annotation_id="745" docOffset="7">
      <en>We hope Mr Berlusconi will be able to leave hospital soon <Alignment alignment="709" annotation_id="803">
          <DiscourseConnective annotation_id="803" sense="Expansion.Conjunction">and</DiscourseConnective>
        </Alignment> we wish him a quick return to health.</en>
      <fr>Nous espérons que M. Berlusconi pourra prochainement quitter l'hôpital <Alignment alignment="803" annotation_id="931">
          <DiscourseConnective annotation_id="931" sense="Expansion.Conjunction">et</DiscourseConnective>
        </Alignment> nous lui souhaitons un prompt rétablissement.</fr>
    </ParallelChunk>
<ParallelChunk annotation_id="845" docOffset="8">
      <en>With your permission, I would <Alignment alignment="1014" annotation_id="875">
          <DiscourseConnective annotation_id="875" sense="Expansion.Conjunction">also</DiscourseConnective>
        </Alignment> like to mention an anniversary which is important to me personally.</en>
      <fr>
        <DiscourseConnective annotation_id="980">Si</DiscourseConnective> vous le permettez, je voudrais <Alignment alignment="283" annotation_id="1014">
          <DiscourseConnective annotation_id="1014" sense="Expansion.Conjunction">également</DiscourseConnective>
        </Alignment> citer un anniversaire qui me tient personnellement à cœur.</fr>
    </ParallelChunk>
<ParallelChunk annotation_id="948" docOffset="9">
      <en>Yesterday, it was 28 years since the imposition of martial law in Poland by the then Communist authorities.</en>
      <fr>Hier, il y a eu 28 ans <DiscourseConnective annotation_id="1106">que</DiscourseConnective> la loi martiale a été imposée <DiscourseConnective annotation_id="1140">en</DiscourseConnective> Pologne par le pouvoir communiste de l'époque.</fr>
    </ParallelChunk>
<ParallelChunk annotation_id="1056" docOffset="10">
      <en>
        <Alignment alignment="1190" annotation_id="1056">
          <DiscourseConnective annotation_id="1056" sense="Contingency.Cause.Result">As a result</DiscourseConnective>
        </Alignment>, almost 100 people lost their lives, including the nine miners who were shot during the strike at the Wujek Mine.</en>
      <fr>
        <Alignment alignment="99" annotation_id="1190">
          <DiscourseConnective annotation_id="1190" sense="Contingency.Cause.Result">À</DiscourseConnective>
        </Alignment> la suite de cela, une centaine de personnes ont perdu la vie, dont neuf mineurs qui ont été tués durant la grève de la mine de Wujek.</fr>
    </ParallelChunk>
<ParallelChunk annotation_id="1182" docOffset="11">
      <en>Many thousands of democratic opposition activists were interned, <Alignment alignment="4959" annotation_id="1247">
          <DiscourseConnective annotation_id="1247" sense="Expansion.Conjunction">and</DiscourseConnective>
        </Alignment> others were even imprisoned. This was intended to break up and destroy the Solidarity trade union.</en>
      <fr>Plusieurs milliers de militants démocratiques de l'opposition furent arrêtés à l'époque <Alignment alignment="322" annotation_id="1414">
          <DiscourseConnective annotation_id="1414" sense="Expansion.Conjunction">et</DiscourseConnective>
        </Alignment> certains furent emprisonnés <DiscourseConnective annotation_id="1445">dans le but de</DiscourseConnective> briser <DiscourseConnective annotation_id="1467">et</DiscourseConnective> d'anéantir le syndicat Solidarité.</fr>
    </ParallelChunk>
<ParallelChunk annotation_id="1350" docOffset="12">
      <en>I refer to these events <DiscourseConnective annotation_id="1374" sense="Contingency.Cause.Reason">because</DiscourseConnective> I would like to draw attention to how greatly Europe has changed in the past two or three decades, but also to how we ought to strive for peace and human rights in our continent and throughout the world.</en>
      <fr>Je fais allusion <DiscourseConnective annotation_id="1522">à</DiscourseConnective> ces événements afin d'attirer votre attention sur les changements considérables <DiscourseConnective annotation_id="1604">qu'</DiscourseConnective>a connus l'Europe au cours de ces vingt <DiscourseConnective annotation_id="1647">ou</DiscourseConnective> trente dernières années, <DiscourseConnective annotation_id="1675">mais aussi</DiscourseConnective> sur la manière dont nous devrions lutter <DiscourseConnective annotation_id="1727">pour</DiscourseConnective> la paix <DiscourseConnective annotation_id="1740">et</DiscourseConnective> les droits de l'homme sur notre continent <DiscourseConnective annotation_id="1785">ainsi</DiscourseConnective> que dans le monde entier.</fr>
    </ParallelChunk>
<ParallelChunk annotation_id="1586" docOffset="13">
      <en>I would <Alignment alignment="1829" annotation_id="1594">
          <DiscourseConnective annotation_id="1594" sense="Expansion.Conjunction">also</DiscourseConnective>
        </Alignment> like to take the opportunity to remind you that on Wednesday at 12.00, a ceremony will be held to present the Sakharov Prize for Freedom of Thought.</en>
      <fr>Je voudrais <Alignment alignment="1358" annotation_id="1829">
          <DiscourseConnective annotation_id="1829" sense="Expansion.Conjunction">aussi</DiscourseConnective>
        </Alignment> profiter de l'occasion <DiscourseConnective annotation_id="1858">pour</DiscourseConnective> vous rappeler <DiscourseConnective annotation_id="1877">que</DiscourseConnective> mercredi prochain <DiscourseConnective annotation_id="1899">à</DiscourseConnective> 12 heures, une cérémonie aura lieu <DiscourseConnective annotation_id="1936">afin de</DiscourseConnective> décerner le prix Sakharov <DiscourseConnective annotation_id="1970">pour</DiscourseConnective> la liberté de pensée.</fr>
    </ParallelChunk>
<ParallelChunk annotation_id="1748" docOffset="14">
      <en>This year, the prize has been awarded to Lyudmila Alexeyeva, Sergei Kovalev and Oleg Orlov, who represent the Russian human rights defence organisation Memorial.</en>
      <fr>Cette année, le prix a été décerné <DiscourseConnective annotation_id="2032">à</DiscourseConnective> Lyudmila Alexeyeva, Sergei Kovalev <DiscourseConnective annotation_id="2069">et</DiscourseConnective> Oleg Orlov, qui représentent l'association russe de défense des droits de l'homme Mémorial.</fr>
    </ParallelChunk>
<ParallelChunk annotation_id="1910" docOffset="15">
      <en>Our continent experienced very great suffering during the 20th century, <Alignment alignment="2234" annotation_id="1982">
          <DiscourseConnective annotation_id="1982" sense="Contingency.Cause.Result">so</DiscourseConnective>
        </Alignment> we understand very well the importance of striving for human rights around the world, and especially in the continent of Europe.</en>
      <fr>Notre continent a connu de grandes souffrances au cours du XXe siècle <Alignment alignment="3047" annotation_id="2234">
          <DiscourseConnective annotation_id="2234" sense="Contingency.Cause.Result">de sorte que</DiscourseConnective>
        </Alignment> nous comprenons parfaitement l'importance de la lutte <DiscourseConnective annotation_id="2301">pour</DiscourseConnective> les droits de l'homme de par le monde <DiscourseConnective annotation_id="2344">et</DiscourseConnective> <DiscourseConnective annotation_id="2347">en particulier</DiscourseConnective> sur le continent européen.</fr>
    </ParallelChunk>
<ParallelChunk annotation_id="2114" docOffset="16">
      <en>This event, <Alignment alignment="2389" annotation_id="2126">
          <DiscourseConnective annotation_id="2126" sense="Contingency.Cause.Result">therefore</DiscourseConnective>
        </Alignment>, holds particular value for us.</en>
      <fr>
        <Alignment alignment="2126" annotation_id="2389">
          <DiscourseConnective annotation_id="2389" sense="Contingency.Cause.Result">C'est pourquoi</DiscourseConnective>
        </Alignment> cette manifestation nous est très chère.</fr>
    </ParallelChunk>
</Speaker>
  <Speaker annotation_id="2168" id="007" language="IT" name="Francesco Enrico Speroni">
    <ParallelChunk annotation_id="2168" docOffset="17">
      <en>Mr President, ladies and gentlemen, apologies <Alignment alignment="2503" annotation_id="2214">
          <DiscourseConnective annotation_id="2214" sense="Contingency.Condition">if</DiscourseConnective>
        </Alignment> I am not speaking in accordance with proper procedure, <Alignment alignment="2562" annotation_id="2272">
          <DiscourseConnective annotation_id="2272" sense="Comparison.Contrast">but</DiscourseConnective>
        </Alignment> I wanted to express my solidarity and that of my group with Prime Minister Berlusconi.</en>
      <fr>Monsieur le Président, Mesdames <DiscourseConnective annotation_id="2477">et</DiscourseConnective> Messieurs, excusez-moi <Alignment alignment="2257" annotation_id="2503">
          <DiscourseConnective annotation_id="2503" sense="Contingency.Condition">si</DiscourseConnective>
        </Alignment> mon intervention ne respecte pas la procédure convenue, <Alignment alignment="2272" annotation_id="2562">
          <DiscourseConnective annotation_id="2562" sense="Comparison.Contrast">mais</DiscourseConnective>
        </Alignment> je voulais exprimer ma solidarité, <DiscourseConnective annotation_id="2602">ainsi</DiscourseConnective> <DiscourseConnective annotation_id="2608">que</DiscourseConnective> celle de mon groupe envers le Premier ministre Berlusconi.</fr>
    </ParallelChunk>
</Speaker>
  <Speaker annotation_id="2363" id="008" name="President">
    <ParallelChunk annotation_id="2363" docOffset="18">
      <en>I was speaking on behalf of the entire European Parliament.</en>
      <fr>Je m'exprimais au nom de l'ensemble du Parlement européen.</fr>
    </ParallelChunk>
</Speaker>
  <Speaker annotation_id="2423" id="009" language="IT" name="Gianni Pittella">
    <ParallelChunk annotation_id="2423" docOffset="19">
      <en>Mr President, ladies and gentlemen, I, together with Mr Sassoli and all the members of the Democratic Party within the Group of the Progressive Alliance of Socialists and Democrats in the European Parliament, would like to echo your words of solidarity towards the Italian Prime Minister, Silvio Berlusconi, and stress that this was an abominable, unacceptable and unjustifiable act.</en>
      <fr>Monsieur le Président, Mesdames <DiscourseConnective annotation_id="2762">et</DiscourseConnective> Messieurs, je m'associe, à l'instar de M. Sassoli <DiscourseConnective annotation_id="2815">et</DiscourseConnective> de l'ensemble des députés du parti démocratique au sein du groupe de l'Alliance progressiste des Socialistes <DiscourseConnective annotation_id="2927">et</DiscourseConnective> Démocrates au Parlement européen, <DiscourseConnective annotation_id="2964">à</DiscourseConnective> vos propos concernant la solidarité envers le Premier ministre italien, M. Silvio Berlusconi, <DiscourseConnective annotation_id="3060">et</DiscourseConnective> je trouve qu'un tel acte est abominable, inacceptable <DiscourseConnective annotation_id="3117">et</DiscourseConnective> injustifiable.</fr>
    </ParallelChunk>
<ParallelChunk annotation_id="2807" docOffset="20">
      <en>We are ardent opponents of Mr Berlusconi, <Alignment alignment="3190" annotation_id="2849">
          <DiscourseConnective annotation_id="2849" sense="Comparison.Contrast">but</DiscourseConnective>
        </Alignment> we are political adversaries.</en>
      <fr>Nous sommes de farouches adversaires de M. Berlusconi, <Alignment alignment="2849" annotation_id="3190">
          <DiscourseConnective annotation_id="3190" sense="Comparison.Contrast">mais</DiscourseConnective>
        </Alignment> nous sommes des adversaires politiques.</fr>
    </ParallelChunk>
<ParallelChunk annotation_id="2883" docOffset="21">
      <en>We do not view Mr Berlusconi, or any other opponent, as our enemy.</en>
      <fr>Nous ne considérons pas M. Berlusconi, <DiscourseConnective annotation_id="3274">ou</DiscourseConnective> tout autre adversaire, <DiscourseConnective annotation_id="3300">comme</DiscourseConnective> notre ennemi.</fr>
    </ParallelChunk>
<ParallelChunk annotation_id="2950" docOffset="22">
      <en>There is no other way to fight and win except through political and civil battle.</en>
      <fr>La seule manière de lutter <DiscourseConnective annotation_id="3347">et</DiscourseConnective> de gagner passe par un combat politique <DiscourseConnective annotation_id="3390">et</DiscourseConnective> civil.</fr>
    </ParallelChunk>
<ParallelChunk annotation_id="3032" docOffset="23">
      <en>We will not allow anyone to force the liveliness of political debate down a dangerous road of hate and violence, which is the first step towards authoritarian and antidemocratic practices.</en>
      <fr>Nous ne permettrons à personne d'entraîner la vivacité du débat politique sur la dangereuse voie de la haine <DiscourseConnective annotation_id="3509">et</DiscourseConnective> de la violence, qui constitue la <DiscourseConnective annotation_id="3545">première étape</DiscourseConnective> vers des pratiques autoritaires <DiscourseConnective annotation_id="3592">et</DiscourseConnective> antidémocratiques.</fr>
    </ParallelChunk>
<ParallelChunk annotation_id="3221" docOffset="24">
      <en>It is right that, once again, this Parliament shows its superior equanimity, respect and democratic maturity.</en>
      <fr>L'Assemblée a bien fait de témoigner une nouvelle fois de son équanimité supérieure, de son respect <DiscourseConnective annotation_id="3714">et</DiscourseConnective> de sa maturité démocratique.</fr>
    </ParallelChunk>
</Speaker>
  <Speaker annotation_id="3331" id="010" language="IT" name="Mario Mauro">
    <ParallelChunk annotation_id="3331" docOffset="25">
      <en>Mr President, ladies and gentlemen, I would like, <Alignment alignment="3808" annotation_id="3381">
          <DiscourseConnective annotation_id="3381" sense="Expansion.Conjunction">also</DiscourseConnective>
        </Alignment> on behalf of my group, to informally offer my truly heartfelt thanks, first of all to you, who labelled what happened in the most appropriate terms, which is to say 'undignified', but even more so, <Alignment alignment="4022" annotation_id="3584">
          <DiscourseConnective annotation_id="3584" sense="Contingency.Condition">if</DiscourseConnective>
        </Alignment> possible, to my Italian fellow Members, and <Alignment alignment="4069" annotation_id="3631">
          <Alignment alignment="4069" annotation_id="3631">
            <DiscourseConnective annotation_id="3631" sense="Expansion.Restatement">in particular</DiscourseConnective>
          </Alignment>
        </Alignment>, Mr Pittella, for their words.</en>
      <fr>Monsieur le Président, Mesdames <DiscourseConnective annotation_id="3778">et</DiscourseConnective> Messieurs, je voudrais moi <Alignment alignment="995" annotation_id="3808">
          <DiscourseConnective annotation_id="3808" sense="Expansion.Conjunction">aussi</DiscourseConnective>
        </Alignment>, au nom de mon groupe, adresser simplement, mais du fond du cœur, mes remerciements <DiscourseConnective annotation_id="3898">avant</DiscourseConnective> tout <DiscourseConnective annotation_id="3909">à</DiscourseConnective> vous qui avez qualifié cet événement d'"indigne", ce qui est un terme tout à fait approprié, <DiscourseConnective annotation_id="4004">mais</DiscourseConnective> <DiscourseConnective annotation_id="4009">encore</DiscourseConnective> plus, <Alignment alignment="3584" annotation_id="4022">
          <DiscourseConnective annotation_id="4022" sense="Contingency.Condition">si</DiscourseConnective>
        </Alignment> c'est possible, <DiscourseConnective annotation_id="4041">à</DiscourseConnective> mes collègues italiens <DiscourseConnective annotation_id="4066">et</DiscourseConnective> <Alignment alignment="369" annotation_id="4069">
          <Alignment alignment="3631" annotation_id="4069">
            <DiscourseConnective annotation_id="4069" sense="Expansion.Restatement">en particulier</DiscourseConnective>
          </Alignment>
        </Alignment> à M. Pittella, <DiscourseConnective annotation_id="4099">pour</DiscourseConnective> leurs propos.</fr>
    </ParallelChunk>
<ParallelChunk annotation_id="3676" docOffset="26">
      <en>I do not intend to engage in political speculation of any kind.</en>
      <fr>Mon intention n'est pas de me lancer dans des spéculations politiques de quelle nature que ce soit.</fr>
    </ParallelChunk>
<ParallelChunk annotation_id="3740" docOffset="27">
      <en>What happened really could take us almost to the edge of the abyss, the precipice, <Alignment alignment="4300" annotation_id="3823">
          <DiscourseConnective annotation_id="3823" sense="Expansion.Conjunction">and</DiscourseConnective>
        </Alignment> <DiscourseConnective annotation_id="3827" sense="Contingency.Cause.Result">so</DiscourseConnective> the unanimous call that came from Parliament is the only one that can guide us at this difficult time.</en>
      <fr>Ce qu'il est arrivé pourrait nous mener presque au bord du gouffre, du précipice, <Alignment alignment="3823" annotation_id="4300">
          <DiscourseConnective annotation_id="4300" sense="Expansion.Conjunction">et</DiscourseConnective>
        </Alignment> l'appel unanime lancé par l'Assemblée est donc le seul qui puisse nous guider <DiscourseConnective annotation_id="4381">en</DiscourseConnective> ce moment difficile.</fr>
    </ParallelChunk>
<ParallelChunk annotation_id="3933" docOffset="28">
      <en>I <Alignment alignment="4417" annotation_id="3935">
          <DiscourseConnective annotation_id="3935" sense="Contingency.Cause.Result">therefore</DiscourseConnective>
        </Alignment> thank Parliament and thank Europe for their contribution to life and to democratic development in Italy.</en>
      <fr>Je remercie <Alignment alignment="3935" annotation_id="4417">
          <DiscourseConnective annotation_id="4417" sense="Contingency.Cause.Result">par conséquent</DiscourseConnective>
        </Alignment> l'Assemblée <DiscourseConnective annotation_id="4444">et</DiscourseConnective> l'Europe <DiscourseConnective annotation_id="4456">pour</DiscourseConnective> leur contribution en faveur de la vie <DiscourseConnective annotation_id="4499">et</DiscourseConnective> de l'évolution démocratique <DiscourseConnective annotation_id="4530">en</DiscourseConnective> Italie.</fr>
    </ParallelChunk>
</Speaker>
</DOCUMENT>
