<?xml version="1.0" encoding="UTF-8"?>
<?xml-stylesheet type="text/xsl" href="translator.xsl"?>

<DOCUMENT>
  <ParallelChunk annotation_id="0" docOffset="0">
    <en>3.</en>
    <fr>3.</fr>
  </ParallelChunk>
<ParallelChunk annotation_id="3" docOffset="1">
    <en>Free trade agreement between the EU and the Republic of Korea (</en>
    <fr>Accord de libre-échange entre l'Union européenne <DiscourseConnective annotation_id="52">et</DiscourseConnective> la République de Corée (</fr>
  </ParallelChunk>
<Speaker annotation_id="67" id="083" name="Robert Sturdy">
    <ParallelChunk annotation_id="67" docOffset="2">
      <en>rapporteur. - Mr President, I know everybody wants to rush off, <Alignment alignment="161" annotation_id="131">
          <DiscourseConnective annotation_id="131" sense="Comparison.Contrast">but</DiscourseConnective>
        </Alignment> I just want to thank the Commission and the shadow rapporteurs on this.</en>
      <fr>rapporteur. - (EN) Monsieur le Président, je sais que tout le monde veut partir, <Alignment alignment="131" annotation_id="161">
          <DiscourseConnective annotation_id="161" sense="Comparison.Contrast">mais</DiscourseConnective>
        </Alignment> je voudrais <DiscourseConnective annotation_id="178">simplement</DiscourseConnective> remercier la Commission <DiscourseConnective annotation_id="213">et</DiscourseConnective> les rapporteurs fictifs <DiscourseConnective annotation_id="240">pour</DiscourseConnective> cet accord.</fr>
    </ParallelChunk>
<ParallelChunk annotation_id="207" docOffset="3">
      <en>This is a ground-breaking free trade agreement, which is outstanding.</en>
      <fr>C'est un accord de libre-échange novateur, ce qui est remarquable.</fr>
    </ParallelChunk>
<ParallelChunk annotation_id="277" docOffset="4">
      <en>Parliament has a huge opportunity to support it and to put forward wonderful ideas for the future.</en>
      <fr>Le Parlement dispose d'une occasion en or de le soutenir <DiscourseConnective annotation_id="381">et</DiscourseConnective> de présenter d'excellentes idées <DiscourseConnective annotation_id="417">pour</DiscourseConnective> l'avenir.</fr>
    </ParallelChunk>
</Speaker>
  <Speaker annotation_id="376" id="084" name="President">
    <ParallelChunk annotation_id="376" docOffset="5">
      <en>I put this fantastic agreement to the vote.</en>
      <fr>Je mets cet accord remarquable au vote.</fr>
    </ParallelChunk>
<ParallelChunk annotation_id="420" docOffset="6">
      <en>It is a roll-call vote.</en>
      <fr>C'est un vote par appel nominal.</fr>
    </ParallelChunk>
<ParallelChunk annotation_id="444" docOffset="7">
      <en>It is carried.</en>
      <fr>Adopté.</fr>
    </ParallelChunk>
<ParallelChunk annotation_id="459" docOffset="8">
      <en>Congratulations to Mr Sturdy.</en>
      <fr>Félicitations <DiscourseConnective annotation_id="527">à</DiscourseConnective> M. Sturdy.</fr>
    </ParallelChunk>
</Speaker>
</DOCUMENT>
