<?xml version="1.0" encoding="UTF-8"?>
<?xml-stylesheet type="text/xsl" href="translator.xsl"?>

<DOCUMENT>
  <ParallelChunk annotation_id="0" docOffset="0">
    <en>3.</en>
    <fr>3.</fr>
  </ParallelChunk>
<ParallelChunk annotation_id="3" docOffset="1">
    <en>Philippines (vote)</en>
    <fr>Philippines (vote)</fr>
  </ParallelChunk>
<Speaker annotation_id="22" id="104" name="Barbara Lochbihler">
    <ParallelChunk annotation_id="22" docOffset="2">
      <en>author. - Mr President, we would like to replace the sentence in paragraph 6 which reads: 'to release all disappeared who are still in captivity'.</en>
      <fr>auteure. - (EN) Monsieur le Président, nous souhaiterions remplacer la phrase suivante du paragraphe 6: "libérer toutes les personnes enlevées qui se trouvent <DiscourseConnective annotation_id="181">encore</DiscourseConnective> <DiscourseConnective annotation_id="188">en</DiscourseConnective> captivité".</fr>
    </ParallelChunk>
<ParallelChunk annotation_id="169" docOffset="3">
      <en>
        <DiscourseConnective annotation_id="169" sense="Expansion.Alternative.Chosen alternative">Instead</DiscourseConnective> we would like to introduce: 'to make every effort to ensure that all who have been abducted are safety returned to their families'.</en>
      <fr>Nous souhaiterions la remplacer par: "mettre <DiscourseConnective annotation_id="248">tout en</DiscourseConnective> œuvre <DiscourseConnective annotation_id="262">pour</DiscourseConnective> s'assurer <DiscourseConnective annotation_id="277">que</DiscourseConnective> toutes les personnes enlevées soient rendues saines et sauves <DiscourseConnective annotation_id="343">à</DiscourseConnective> leurs familles".</fr>
    </ParallelChunk>
</Speaker>
</DOCUMENT>
