<?xml version="1.0" encoding="UTF-8"?>
<?xml-stylesheet type="text/xsl" href="translator.xsl"?>

<DOCUMENT>
  <ParallelChunk annotation_id="0" docOffset="0">
    <en>6.</en>
    <fr>6.</fr>
  </ParallelChunk>
<ParallelChunk annotation_id="3" docOffset="1">
    <en>Approach of the European Parliament to implementing Articles 9 and 10 of Protocol 1 of the Lisbon Treaty on parliamentary cooperation in the field of CFSP/CSDP (</en>
    <fr>Approche du Parlement européen relative <DiscourseConnective annotation_id="43">à</DiscourseConnective> la mise en œuvre des articles 9 <DiscourseConnective annotation_id="77">et</DiscourseConnective> 10 du protocole n° 1 du traité de Lisbonne sur la coopération parlementaire dans le domaine de la PESC/PSDC (</fr>
  </ParallelChunk>
</DOCUMENT>
